clip/__init__.py
clip/bpe_simple_vocab_16e6.txt.gz
clip/clip.py
clip/model.py
clip/simple_tokenizer.py
visaionclip_118_202511031429-1.0.dist-info/licenses/LICENSE
visaionclip_118_202511031429-1.0.dist-info/METADATA
visaionclip_118_202511031429-1.0.dist-info/WHEEL
visaionclip_118_202511031429-1.0.dist-info/top_level.txt
visaionclip_118_202511031429-1.0.dist-info/RECORD
